LICENSE
README.md
setup.cfg
setup.py
ptmux/__init__.py
ptmux.egg-info/PKG-INFO
ptmux.egg-info/SOURCES.txt
ptmux.egg-info/dependency_links.txt
ptmux.egg-info/requires.txt
ptmux.egg-info/top_level.txt